urllib3/__init__.py
urllib3/_collections.py
urllib3/_constant.py
urllib3/_request_methods.py
urllib3/_typing.py
urllib3/_version.py
urllib3/connection.py
urllib3/connectionpool.py
urllib3/exceptions.py
urllib3/fields.py
urllib3/filepost.py
urllib3/poolmanager.py
urllib3/py.typed
urllib3/response.py
urllib3/_async/__init__.py
urllib3/_async/connection.py
urllib3/_async/connectionpool.py
urllib3/_async/poolmanager.py
urllib3/_async/response.py
urllib3/backend/__init__.py
urllib3/backend/_base.py
urllib3/backend/hface.py
urllib3/backend/_async/__init__.py
urllib3/backend/_async/_base.py
urllib3/backend/_async/hface.py
urllib3/contrib/__init__.py
urllib3/contrib/_socks_legacy.py
urllib3/contrib/_socks_override.py
urllib3/contrib/pyopenssl.py
urllib3/contrib/socks.py
urllib3/contrib/emscripten/__init__.py
urllib3/contrib/hface/__init__.py
urllib3/contrib/hface/_configuration.py
urllib3/contrib/hface/_stream_matrix.py
urllib3/contrib/hface/_typing.py
urllib3/contrib/hface/py.typed
urllib3/contrib/hface/events/__init__.py
urllib3/contrib/hface/events/_events.py
urllib3/contrib/hface/protocols/__init__.py
urllib3/contrib/hface/protocols/_factories.py
urllib3/contrib/hface/protocols/_protocols.py
urllib3/contrib/hface/protocols/http1/__init__.py
urllib3/contrib/hface/protocols/http1/_h11.py
urllib3/contrib/hface/protocols/http2/__init__.py
urllib3/contrib/hface/protocols/http2/_h2.py
urllib3/contrib/hface/protocols/http3/__init__.py
urllib3/contrib/hface/protocols/http3/_qh3.py
urllib3/contrib/imcc/__init__.py
urllib3/contrib/imcc/_ctypes.py
urllib3/contrib/imcc/_shm.py
urllib3/contrib/resolver/__init__.py
urllib3/contrib/resolver/factories.py
urllib3/contrib/resolver/protocols.py
urllib3/contrib/resolver/utils.py
urllib3/contrib/resolver/_async/__init__.py
urllib3/contrib/resolver/_async/factories.py
urllib3/contrib/resolver/_async/protocols.py
urllib3/contrib/resolver/_async/doh/__init__.py
urllib3/contrib/resolver/_async/doh/_urllib3.py
urllib3_future-2.14.904.dist-info/METADATA
urllib3_future-2.14.904.dist-info/WHEEL
urllib3_future-2.14.904.dist-info/licenses/LICENSE.txt
urllib3_future-2.14.904.dist-info/RECORD
