Metadata-Version: 2.4
Name: urllib3-future
Version: 2.14.904
Summary: urllib3.future is a powerful HTTP 1.1, 2, and 3 client with both sync and async interfaces
Project-URL: Changelog, https://github.com/jawah/urllib3.future/blob/main/CHANGES.rst
Project-URL: Documentation, https://urllib3future.readthedocs.io
Project-URL: Code, https://github.com/jawah/urllib3.future
Project-URL: Issue tracker, https://github.com/jawah/urllib3.future/issues
Author-email: Andrey Petrov <andrey.petrov@shazow.net>
Maintainer-email: "Ahmed R. TAHRI" <tahri.ahmed@proton.me>
License-Expression: MIT
License-File: LICENSE.txt
Keywords: async,concurrent,dns,dns-over-https,dns-over-quic,dns-over-tls,doh,doq,dot,dou,filepost,http,httplib,https,multiplexed,pooling,ssl,tasksafe,threadsafe,urllib
Classifier: Environment :: Web Environment
Classifier: Intended Audience :: Developers
Classifier: License :: OSI Approved :: MIT License
Classifier: Operating System :: OS Independent
Classifier: Programming Language :: Python
Classifier: Programming Language :: Python :: 3
Classifier: Programming Language :: Python :: 3 :: Only
Classifier: Programming Language :: Python :: 3.7
Classifier: Programming Language :: Python :: 3.8
Classifier: Programming Language :: Python :: 3.9
Classifier: Programming Language :: Python :: 3.10
Classifier: Programming Language :: Python :: 3.11
Classifier: Programming Language :: Python :: 3.12
Classifier: Programming Language :: Python :: 3.13
Classifier: Programming Language :: Python :: 3.14
Classifier: Programming Language :: Python :: Implementation :: CPython
Classifier: Programming Language :: Python :: Implementation :: PyPy
Classifier: Topic :: Internet :: WWW/HTTP
Classifier: Topic :: Software Development :: Libraries
Requires-Python: >=3.7
Requires-Dist: h11<1.0.0,>=0.11.0
Requires-Dist: jh2<6.0.0,>=5.0.3
Requires-Dist: qh3<2.0.0,>=1.5.4; (platform_python_implementation != 'CPython' or python_full_version > '3.7.10') and (platform_system == 'Darwin' or platform_system == 'Windows' or platform_system == 'Linux') and (platform_machine == 'x86_64' or platform_machine == 's390x' or platform_machine == 'armv7l' or platform_machine == 'ppc64le' or platform_machine == 'ppc64' or platform_machine == 'AMD64' or platform_machine == 'aarch64' or platform_machine == 'arm64' or platform_machine == 'ARM64' or 
Provides-Extra: brotli
Requires-Dist: brotli>=1.0.9; (platform_python_implementation == 'CPython') and extra == 'brotli'
Requires-Dist: brotlicffi>=0.8.0; (platform_python_implementation != 'CPython') and extra == 'brotli'
Provides-Extra: qh3
Requires-Dist: qh3<2.0.0,>=1.5.4; extra == 'qh3'
Provides-Extra: secure
Provides-Extra: socks
Requires-Dist: python-socks<=2.6.1,>=2.0; extra == 'socks'
Provides-Extra: ws
Requires-Dist: wsproto<2,>=1.2; extra == 'ws'
Provides-Extra: zstd
Requires-Dist: zstandard>=0.18.0; (python_version < '3.14') and extra == 'zstd'
